README.rst
setup.py
simalq/__init__.py
simalq/__main__.hy
simalq/cmdline.hy
simalq/color.hy
simalq/commands.hy
simalq/display.hy
simalq/game_state.hy
simalq/geometry.hy
simalq/keyboard.hy
simalq/macros.hy
simalq/main.hy
simalq/quest.hy
simalq/save_load.hy
simalq/strings.hy
simalq/un_iq.hy
simalq/util.hy
simalq.egg-info/PKG-INFO
simalq.egg-info/SOURCES.txt
simalq.egg-info/dependency_links.txt
simalq.egg-info/requires.txt
simalq.egg-info/top_level.txt
simalq/quest_definition/__init__.hy
simalq/quest_definition/tower.hy
simalq/quest_definition/tutorial.hy
simalq/tile/__init__.hy
simalq/tile/item.hy
simalq/tile/monster.hy
simalq/tile/player.hy
simalq/tile/scenery.hy
simalq/tile/tilepedia.hy
simalq/tile/unimplemented.hy
tests/__init__.py