Metadata-Version: 2.4
Name: simalq
Version: 2.1.0
Summary: Infinitesimal Quest 2 + ε: A turn-based puzzling dungeon crawler
Author: Kodi B. Arfer
Project-URL: Homepage, http://hylang.org/simalq
Project-URL: Source Code, https://github.com/hylang/simalq
Classifier: License :: OSI Approved :: GNU General Public License v3 or later (GPLv3+)
Classifier: Operating System :: OS Independent
Classifier: Programming Language :: Hy
Classifier: Topic :: Games/Entertainment :: Puzzle Games
Requires-Python: >= 3.10
Requires-Dist: hy>=1
Requires-Dist: hyrule>=1
Requires-Dist: toolz>=1
Requires-Dist: construct>=2.10.70
Requires-Dist: blessed>=1.20.0
Requires-Dist: platformdirs>=4.3.6
Requires-Dist: metadict>=0.1.3
Dynamic: author
Dynamic: classifier
Dynamic: description
Dynamic: description-content-type
Dynamic: project-url
Dynamic: requires-dist
Dynamic: requires-python
Dynamic: summary
